docs_translate/__init__.py
docs_translate/app.py
docs_translate/const.py
docs_translate/exceptions.py
docs_translate/file_translator.py
docs_translate/files_worker.py
docs_translate/google_v2.py
docs_translate/line_processor.py
docs_translate/logs.py
docs_translate/reserved_word.py
docs_translate/settings.py
docs_translate/translator.py
docs_translate/util.py
docs_translate-0.1.6.dist-info/entry_points.txt
docs_translate-0.1.6.dist-info/LICENSE
docs_translate-0.1.6.dist-info/WHEEL
docs_translate-0.1.6.dist-info/METADATA
docs_translate-0.1.6.dist-info/RECORD
