Metadata-Version: 2.1
Name: docs-translate
Version: 0.1.6
Summary: CLI tool to translate markdown and reStructuredText files
Home-page: https://github.com/gs-kikim/docs-trans-app
License: MIT
Author: kyeongin kim
Author-email: kikim@gmail.com
Requires-Python: >=3.6,<4.0
Classifier: Environment :: Console
Classifier: Intended Audience :: Developers
Classifier: Intended Audience :: End Users/Desktop
Classifier: License :: OSI Approved :: MIT License
Classifier: Operating System :: Microsoft :: Windows
Classifier: Operating System :: POSIX :: Linux
Classifier: Programming Language :: Python
Classifier: Programming Language :: Python :: 3
Classifier: Programming Language :: Python :: 3 :: Only
Classifier: Programming Language :: Python :: 3.6
Classifier: Programming Language :: Python :: 3.7
Classifier: Programming Language :: Python :: 3.8
Classifier: Programming Language :: Python :: 3.9
Classifier: Topic :: Documentation
Classifier: Topic :: Utilities
Classifier: Typing :: Typed
Requires-Dist: google-cloud-translate (>=2.0.1,<3.0.0)
Requires-Dist: langdetect (>=1.0.8,<2.0.0)
Requires-Dist: loguru (>=0.5.3,<0.6.0)
Requires-Dist: requests (>=2.24.0,<3.0.0)
Requires-Dist: translators (>=4.7.2,<5.0.0)
Project-URL: Repository, https://github.com/gs-kikim/docs-trans-app
